slack_wordcloud/__init__.py
slack_wordcloud/__main__.py
slack_wordcloud/cli.py
slack_wordcloud/wc.py
slack_wordcloud/commands/GenerateWordCloud.py
slack_wordcloud/commands/SlackHistory.py
slack_wordcloud/commands/__init__.py
slack_wordcloud/commands/base.py
slack_wordcloud/commands/generate.py
slack_wordcloud/commands/generate_base.py
slack_wordcloud/commands/hello.py
slack_wordcloud-0.4a0.dist-info/LICENSE
slack_wordcloud-0.4a0.dist-info/METADATA
slack_wordcloud-0.4a0.dist-info/WHEEL
slack_wordcloud-0.4a0.dist-info/entry_points.txt
slack_wordcloud-0.4a0.dist-info/top_level.txt
slack_wordcloud-0.4a0.dist-info/RECORD
