Metadata-Version: 2.1
Name: slack-wordcloud
Version: 0.4a0
Summary: Generate word clouds for Slack channels!
Home-page: https://github.com/angel-hernandez91/slack-wordcloud
Author: Angel Hernandez
Author-email: ahernandez0691@gmail.com
License: MIT
Keywords: cli,slack,wordcloud,app
Platform: UNKNOWN
Classifier: Programming Language :: Python :: 3
Classifier: License :: OSI Approved :: MIT License
Classifier: Operating System :: OS Independent
Requires-Dist: docopt
